donbot/__init__.py
donbot/donbot.py
donbot/operations.py
donbot_python-0.2.1.dist-info/LICENSE
donbot_python-0.2.1.dist-info/METADATA
donbot_python-0.2.1.dist-info/WHEEL
donbot_python-0.2.1.dist-info/top_level.txt
donbot_python-0.2.1.dist-info/RECORD
