Metadata-Version: 2.1
Name: donbot-python
Version: 0.2.1
Summary: a Python library for automating activities on mafiascum.net
Home-page: https://github.com/Computational-Mafia/donbot
Author: Jordan Gunn
Author-email: gunnjordanb@gmail.com
Classifier: Development Status :: 3 - Alpha
Classifier: Intended Audience :: Developers
Classifier: License :: OSI Approved :: GNU General Public License v3 (GPLv3)
Classifier: Programming Language :: Python :: 3
Classifier: Programming Language :: Python :: 3.7
Classifier: Programming Language :: Python :: 3.8
Classifier: Programming Language :: Python :: 3.9
Requires-Python: >=3.7
License-File: LICENSE
Requires-Dist: lxml
